[
  {
    "package": "CPGLIB",
    "maintainer": "Anthony Christidis <anthony.christidis@stat.ubc.ca>",
    "url": "https://github.com/anthonychristidis/cpglib",
    "available": true
  },
  {
    "package": "nnGarrote",
    "maintainer": "Anthony Christidis <anthony.christidis@stat.ubc.ca>",
    "url": "https://github.com/anthonychristidis/nngarrote",
    "available": true
  },
  {
    "package": "PSGD",
    "maintainer": "Anthony Christidis <anthony.christidis@stat.ubc.ca>",
    "url": "https://github.com/anthonychristidis/psgd",
    "available": true
  },
  {
    "package": "RPEGLMEN",
    "maintainer": "Anthony Christidis <anthony.christidis@stat.ubc.ca>",
    "url": "https://github.com/cran/RPEGLMEN"
  },
  {
    "package": "RPEIF",
    "maintainer": "Anthony Christidis <anthony.christidis@stat.ubc.ca>",
    "url": "https://github.com/anthonychristidis/rpeif",
    "available": true
  },
  {
    "package": "RPESE",
    "maintainer": "Anthony Christidis <anthony.christidis@stat.ubc.ca>",
    "url": "https://github.com/anthonychristidis/rpese",
    "available": true
  },
  {
    "package": "simTargetCov",
    "maintainer": "Anthony Christidis <anthony.christidis@stat.ubc.ca>",
    "url": "https://github.com/anthonychristidis/simtargetcov",
    "available": true
  },
  {
    "package": "SplitGLM",
    "maintainer": "Anthony Christidis <anthony.christidis@stat.ubc.ca>",
    "url": "https://github.com/anthonychristidis/splitglm",
    "available": true
  },
  {
    "package": "SplitReg",
    "maintainer": "Anthony Christidis <anthony.christidis@stat.ubc.ca>",
    "url": "https://github.com/anthonychristidis/splitreg",
    "available": true
  },
  {
    "package": "splitSelect",
    "maintainer": "Anthony Christidis <anthony.christidis@stat.ubc.ca>",
    "url": "https://github.com/anthonychristidis/splitselect",
    "available": true
  },
  {
    "package": "stepSplitReg",
    "maintainer": "Anthony Christidis <anthony.christidis@stat.ubc.ca>",
    "url": "https://github.com/anthonychristidis/stepsplitreg",
    "available": true
  }
]
