[
  {
    "package": "amap",
    "maintainer": "Antoine Lucas <antoinelucas@gmail.com>",
    "url": "https://github.com/cran/amap"
  },
  {
    "package": "ctc",
    "maintainer": "Antoine Lucas <antoinelucas@gmail.com>",
    "url": "https://git.bioconductor.org/packages/ctc",
    "registry": "bioc"
  },
  {
    "package": "geotools",
    "maintainer": "Antoine Lucas <antoinelucas@gmail.com>",
    "url": "https://github.com/cran/geotools"
  },
  {
    "package": "gmp",
    "maintainer": "Antoine Lucas <antoinelucas@gmail.com>",
    "url": "https://github.com/cran/gmp"
  }
]
