[
  {
    "package": "augmentedRCBD",
    "maintainer": "J. Aravind <j.aravind@icar.gov.in>",
    "url": "https://github.com/aravind-j/augmentedrcbd",
    "available": true
  },
  {
    "package": "EvaluateCore",
    "maintainer": "J. Aravind <j.aravind@icar.gov.in>",
    "url": "https://github.com/aravind-j/evaluatecore",
    "available": true
  },
  {
    "package": "germinationmetrics",
    "maintainer": "J. Aravind <j.aravind@icar.gov.in>",
    "url": "https://github.com/aravind-j/germinationmetrics",
    "available": true
  },
  {
    "package": "PGRdup",
    "maintainer": "J. Aravind <j.aravind@icar.gov.in>",
    "url": "https://github.com/aravind-j/pgrdup",
    "available": true
  },
  {
    "package": "rmelting",
    "maintainer": "J. Aravind <j.aravind@icar.gov.in>",
    "url": "https://github.com/aravind-j/rmelting",
    "available": true,
    "registry": "bioc"
  }
]
