[
  {
    "package": "disbayes",
    "maintainer": "Christopher Jackson <chris.jackson@mrc-bsu.cam.ac.uk>",
    "url": "https://github.com/chjackson/disbayes",
    "available": false
  },
  {
    "package": "fic",
    "maintainer": "Christopher Jackson <chris.jackson@mrc-bsu.cam.ac.uk>",
    "url": "https://github.com/chjackson/fic",
    "available": true
  },
  {
    "package": "flexsurv",
    "maintainer": "Christopher Jackson <chris.jackson@mrc-bsu.cam.ac.uk>",
    "url": "https://github.com/chjackson/flexsurv-dev",
    "available": true
  },
  {
    "package": "MetaAnalyser",
    "maintainer": "Christopher Jackson <chris.jackson@mrc-bsu.cam.ac.uk>",
    "url": "https://github.com/chjackson/metaanalyser",
    "available": false
  },
  {
    "package": "msm",
    "maintainer": "Christopher Jackson <chris.jackson@mrc-bsu.cam.ac.uk>",
    "url": "https://github.com/chjackson/msm",
    "available": true
  }
]
