[
  {
    "package": "cbinom",
    "maintainer": "Dan Dalthorp <ddalthorp@protonmail.com>",
    "url": "https://github.com/ddalthorp/cbinom"
  },
  {
    "package": "dwp",
    "maintainer": "Daniel Dalthorp <ddalthorp@protonmail.com>",
    "url": "https://github.com/ddalthorp/dwp",
    "registry": "archived"
  },
  {
    "package": "eoa3",
    "maintainer": "Daniel Dalthorp <ddalthorp@protonmail.com>",
    "url": "https://github.com/ddalthorp/eoa3",
    "registry": "archived"
  },
  {
    "package": "GenEst",
    "maintainer": "Daniel Dalthorp <ddalthorp@protonmail.com>",
    "url": "https://github.com/ddalthorp/genest",
    "registry": "archived"
  }
]
