[
  {
    "package": "deseats",
    "maintainer": "Dominik Schulz <dominik.schulz@uni-paderborn.de>",
    "url": "https://github.com/cran/deseats"
  },
  {
    "package": "esemifar",
    "maintainer": "Dominik Schulz <dominik.schulz@uni-paderborn.de>",
    "url": "https://github.com/cran/esemifar"
  },
  {
    "package": "fEGarch",
    "maintainer": "Dominik Schulz <dominik.schulz@uni-paderborn.de>",
    "url": "https://github.com/cran/fEGarch"
  },
  {
    "package": "smoots",
    "maintainer": "Dominik Schulz <schulzd@mail.uni-paderborn.de>",
    "url": "https://github.com/cran/smoots"
  }
]
