[
  {
    "package": "distillery",
    "maintainer": "Eric Gilleland <eric.gilleland@colostate.edu>",
    "url": "https://github.com/cran/distillery"
  },
  {
    "package": "extRemes",
    "maintainer": "Eric Gilleland <eric.gilleland@colostate.edu>",
    "url": "https://github.com/cran/extRemes"
  },
  {
    "package": "ismev",
    "maintainer": "Eric Gilleland <eric.gilleland@colostate.edu>",
    "url": "https://github.com/cran/ismev"
  },
  {
    "package": "smoothie",
    "maintainer": "Eric Gilleland <eric.gilleland@colostate.edu>",
    "url": "https://github.com/cran/smoothie"
  },
  {
    "package": "SpatialVx",
    "maintainer": "Eric Gilleland <eric.gilleland@colostate.edu>",
    "url": "https://github.com/cran/SpatialVx"
  },
  {
    "package": "verification",
    "maintainer": "Eric Gilleland <eric.gilleland@colostate.edu>",
    "url": "https://github.com/cran/verification"
  }
]
