[
  {
    "package": "bioseq",
    "maintainer": "Francois Keck <francois.keck@gmail.com>",
    "url": "https://github.com/fkeck/bioseq"
  },
  {
    "package": "phylosignal",
    "maintainer": "Francois Keck <francois.keck@gmail.com>",
    "url": "https://github.com/fkeck/phylosignal",
    "registry": "archived"
  },
  {
    "package": "refdb",
    "maintainer": "Francois Keck <francois.keck@gmail.com>",
    "url": "https://github.com/fkeck/refdb"
  },
  {
    "package": "rleafmap",
    "maintainer": "Francois Keck <francois.keck@gmail.com>",
    "url": "https://github.com/fkeck/rleafmap"
  }
]
