[
  {
    "package": "bsynth",
    "maintainer": "Ignacio Martinez <ignacio@martinez.fyi>",
    "url": "https://github.com/google/bsynth"
  },
  {
    "package": "CausalImpact",
    "maintainer": "Alain Hauser <alhauser@google.com>",
    "url": "https://github.com/google/causalimpact"
  },
  {
    "package": "imt",
    "maintainer": "Ignacio Martinez <martinezig@google.com>",
    "url": "https://github.com/google/imt"
  },
  {
    "package": "patrick",
    "maintainer": "Michael Quinn <msquinn@google.com>",
    "url": "https://github.com/google/patrick"
  }
]
