[
  {
    "package": "badger",
    "maintainer": "Guangchuang Yu <guangchuangyu@gmail.com>",
    "url": "https://github.com/guangchuangyu/badger",
    "available": true
  },
  {
    "package": "dlstats",
    "maintainer": "Guangchuang Yu <guangchuangyu@gmail.com>",
    "url": "https://github.com/guangchuangyu/dlstats",
    "available": false
  },
  {
    "package": "emojifont",
    "maintainer": "Guangchuang Yu <guangchuangyu@gmail.com>",
    "url": "https://github.com/guangchuangyu/emojifont",
    "available": true
  },
  {
    "package": "ggimage",
    "maintainer": "Guangchuang Yu <guangchuangyu@gmail.com>",
    "url": "https://github.com/guangchuangyu/ggimage",
    "available": true
  },
  {
    "package": "ggplotify",
    "maintainer": "Guangchuang Yu <guangchuangyu@gmail.com>",
    "url": "https://github.com/guangchuangyu/ggplotify",
    "available": true
  },
  {
    "package": "hexSticker",
    "maintainer": "Guangchuang Yu <guangchuangyu@gmail.com>",
    "url": "https://github.com/guangchuangyu/hexsticker",
    "available": true
  },
  {
    "package": "meme",
    "maintainer": "Guangchuang Yu <guangchuangyu@gmail.com>",
    "url": "https://github.com/guangchuangyu/meme",
    "available": true
  },
  {
    "package": "rvcheck",
    "maintainer": "Guangchuang Yu <guangchuangyu@gmail.com>",
    "url": "https://github.com/guangchuangyu/rvcheck",
    "available": true
  },
  {
    "package": "shadowtext",
    "maintainer": "Guangchuang Yu <guangchuangyu@gmail.com>",
    "url": "https://github.com/guangchuangyu/shadowtext",
    "available": true
  },
  {
    "package": "enrichplot",
    "maintainer": "Guangchuang Yu <guangchuangyu@gmail.com>",
    "url": "https://github.com/guangchuangyu/enrichplot",
    "available": true,
    "registry": "bioc"
  },
  {
    "package": "meshes",
    "maintainer": "Guangchuang Yu <guangchuangyu@gmail.com>",
    "url": "https://github.com/guangchuangyu/meshes",
    "available": false,
    "registry": "bioc"
  },
  {
    "package": "ReactomePA",
    "maintainer": "Guangchuang Yu <guangchuangyu@gmail.com>",
    "url": "https://github.com/guangchuangyu/reactomepa",
    "available": false,
    "registry": "bioc"
  },
  {
    "package": "seqcombo",
    "maintainer": "Guangchuang Yu <guangchuangyu@gmail.com>",
    "url": "https://github.com/guangchuangyu/seqcombo",
    "available": false,
    "registry": "bioc"
  }
]
