[
  {
    "package": "brickset",
    "maintainer": "Jason Bryer <jason@bryer.org>",
    "url": "https://github.com/jbryer/brickset",
    "available": true
  },
  {
    "package": "likert",
    "maintainer": "Jason Bryer <jason@bryer.org>",
    "url": "https://github.com/jbryer/likert",
    "available": true
  },
  {
    "package": "multilevelPSA",
    "maintainer": "Jason Bryer <jason@bryer.org>",
    "url": "https://github.com/jbryer/multilevelpsa",
    "available": true
  },
  {
    "package": "PSAboot",
    "maintainer": "Jason Bryer <jason@bryer.org>",
    "url": "https://github.com/jbryer/psaboot",
    "available": true
  },
  {
    "package": "PSAgraphics",
    "maintainer": "Jason Bryer <jason@bryer.org>",
    "url": "https://github.com/jbryer/psagraphics",
    "available": true
  },
  {
    "package": "TriMatch",
    "maintainer": "Jason Bryer <jason@bryer.org>",
    "url": "https://github.com/jbryer/trimatch",
    "available": true
  }
]
