[
  {
    "package": "ifaTools",
    "maintainer": "Joshua N. Pritikin <jpritikin@pobox.com>",
    "url": "https://github.com/jpritikin/ifatools",
    "available": true
  },
  {
    "package": "pcFactorStan",
    "maintainer": "Joshua N. Pritikin <jpritikin@pobox.com>",
    "url": "https://github.com/jpritikin/pcfactorstan",
    "available": true
  },
  {
    "package": "rpf",
    "maintainer": "Joshua Pritikin <jpritikin@pobox.com>",
    "url": "https://github.com/jpritikin/rpf",
    "available": true
  }
]
