[
  {
    "package": "gluedown",
    "maintainer": "Kiernan Nicholls <kiernann@protonmail.com>",
    "url": "https://github.com/kiernann/gluedown",
    "available": true
  },
  {
    "package": "usa",
    "maintainer": "Kiernan Nicholls <kiernann@protonmail.com>",
    "url": "https://github.com/kiernann/usa",
    "available": true
  },
  {
    "package": "whatr",
    "maintainer": "Kiernan Nicholls <kiernann@protonmail.com>",
    "url": "https://github.com/kiernann/whatr",
    "available": true
  }
]
