[
  {
    "package": "exuber",
    "maintainer": "Kostas Vasilopoulos <k.vasilopoulo@gmail.com>",
    "url": "https://github.com/kvasilopoulos/exuber",
    "available": true
  },
  {
    "package": "ihpdr",
    "maintainer": "Kostas Vasilopoulos <k.vasilopoulo@gmail.com>",
    "url": "https://github.com/kvasilopoulos/ihpdr",
    "available": true
  },
  {
    "package": "ivx",
    "maintainer": "Kostas Vasilopoulos <k.vasilopoulo@gmail.com>",
    "url": "https://github.com/kvasilopoulos/ivx",
    "available": true
  },
  {
    "package": "nationwider",
    "maintainer": "Kostas Vasilopoulos <k.vasilopoulo@gmail.com>",
    "url": "https://github.com/kvasilopoulos/nationwider",
    "available": true
  },
  {
    "package": "onsr",
    "maintainer": "Kostas Vasilopoulos <k.vasilopoulo@gmail.com>",
    "url": "https://github.com/kvasilopoulos/onsr",
    "available": true
  },
  {
    "package": "transx",
    "maintainer": "Kostas Vasilopoulos <k.vasilopoulo@gmail.com>",
    "url": "https://github.com/kvasilopoulos/transx",
    "available": true
  },
  {
    "package": "uklr",
    "maintainer": "Kostas Vasilopoulos <k.vasilopoulo@gmail.com>",
    "url": "https://github.com/kvasilopoulos/uklr",
    "available": true
  }
]
