[
  {
    "package": "prospectr",
    "maintainer": "Leonardo Ramirez-Lopez <ramirez.lopez.leo@gmail.com>",
    "url": "https://github.com/l-ramirez-lopez/prospectr"
  },
  {
    "package": "proximetricsR",
    "maintainer": "Leonardo Ramirez-Lopez <ramirez-lopez.l@buchi.com>",
    "url": "https://github.com/l-ramirez-lopez/proximetricsr"
  },
  {
    "package": "resemble",
    "maintainer": "Leonardo Ramirez-Lopez <ramirez.lopez.leo@gmail.com>",
    "url": "https://github.com/l-ramirez-lopez/resemble"
  }
]
