[
  {
    "package": "diffcyt",
    "maintainer": "Lukas M. Weber <lmweberedu@gmail.com>",
    "url": "https://github.com/lmweber/diffcyt",
    "registry": "bioc"
  },
  {
    "package": "ggspavis",
    "maintainer": "Lukas M. Weber <lmweberedu@gmail.com>",
    "url": "https://github.com/lmweber/ggspavis",
    "registry": "bioc"
  },
  {
    "package": "nnSVG",
    "maintainer": "Lukas M. Weber <lmweberedu@gmail.com>",
    "url": "https://github.com/lmweber/nnsvg",
    "registry": "bioc"
  },
  {
    "package": "regsplice",
    "maintainer": "Lukas M. Weber <lukas.weber.edu@gmail.com>",
    "url": "https://github.com/lmweber/regsplice",
    "registry": "bioc"
  },
  {
    "package": "smoothclust",
    "maintainer": "Lukas M. Weber <lmweberedu@gmail.com>",
    "url": "https://github.com/lmweber/smoothclust",
    "registry": "bioc"
  }
]
