[
  {
    "package": "BayesMallows",
    "maintainer": "Oystein Sorensen <oystein.sorensen.1985@gmail.com>",
    "url": "https://github.com/ocbe-uio/bayesmallows"
  },
  {
    "package": "BayesSurvive",
    "maintainer": "Zhi Zhao <zhi.zhao@medisin.uio.no>",
    "url": "https://github.com/ocbe-uio/bayessurvive"
  },
  {
    "package": "cellmigRation",
    "maintainer": "Waldir Leoncio <w.l.netto@medisin.uio.no>",
    "url": "https://github.com/ocbe-uio/cellmigration",
    "registry": "bioc"
  },
  {
    "package": "contingencytables",
    "maintainer": "Waldir Leoncio <w.l.netto@medisin.uio.no>",
    "url": "https://github.com/ocbe-uio/contingencytables"
  },
  {
    "package": "DIscBIO",
    "maintainer": "Waldir Leoncio <w.l.netto@medisin.uio.no>",
    "url": "https://github.com/ocbe-uio/discbio"
  },
  {
    "package": "EnrichIntersect",
    "maintainer": "Zhi Zhao <zhi.zhao@medisin.uio.no>",
    "url": "https://github.com/ocbe-uio/enrichintersect"
  },
  {
    "package": "matlab2r",
    "maintainer": "Waldir Leoncio <w.l.netto@medisin.uio.no>",
    "url": "https://github.com/ocbe-uio/matlab2r"
  },
  {
    "package": "permChacko",
    "maintainer": "Waldir Leoncio <w.l.netto@medisin.uio.no>",
    "url": "https://github.com/ocbe-uio/permchacko"
  },
  {
    "package": "psbcSpeedUp",
    "maintainer": "Zhi Zhao <zhi.zhao@medisin.uio.no>",
    "url": "https://github.com/ocbe-uio/psbcspeedup"
  },
  {
    "package": "TruncExpFam",
    "maintainer": "Waldir Leoncio <w.l.netto@medisin.uio.no>",
    "url": "https://github.com/ocbe-uio/truncexpfam"
  }
]
