[
  {
    "package": "anscombiser",
    "maintainer": "Paul J. Northrop <p.northrop@ucl.ac.uk>",
    "url": "https://github.com/paulnorthrop/anscombiser",
    "available": true
  },
  {
    "package": "bang",
    "maintainer": "Paul J. Northrop <p.northrop@ucl.ac.uk>",
    "url": "https://github.com/paulnorthrop/bang",
    "available": true
  },
  {
    "package": "chandwich",
    "maintainer": "Paul J. Northrop <p.northrop@ucl.ac.uk>",
    "url": "https://github.com/paulnorthrop/chandwich",
    "available": true
  },
  {
    "package": "donut",
    "maintainer": "Paul J. Northrop <p.northrop@ucl.ac.uk>",
    "url": "https://github.com/paulnorthrop/donut",
    "available": true
  },
  {
    "package": "exdex",
    "maintainer": "Paul J. Northrop <p.northrop@ucl.ac.uk>",
    "url": "https://github.com/paulnorthrop/exdex",
    "available": true
  },
  {
    "package": "itp",
    "maintainer": "Paul J. Northrop <p.northrop@ucl.ac.uk>",
    "url": "https://github.com/paulnorthrop/itp",
    "available": true
  },
  {
    "package": "lax",
    "maintainer": "Paul J. Northrop <p.northrop@ucl.ac.uk>",
    "url": "https://github.com/paulnorthrop/lax",
    "available": true
  },
  {
    "package": "lite",
    "maintainer": "Paul J. Northrop <p.northrop@ucl.ac.uk>",
    "url": "https://github.com/paulnorthrop/lite",
    "available": true
  },
  {
    "package": "revdbayes",
    "maintainer": "Paul J. Northrop <p.northrop@ucl.ac.uk>",
    "url": "https://github.com/paulnorthrop/revdbayes",
    "available": true
  },
  {
    "package": "rust",
    "maintainer": "Paul J. Northrop <p.northrop@ucl.ac.uk>",
    "url": "https://github.com/paulnorthrop/rust",
    "available": true
  },
  {
    "package": "smovie",
    "maintainer": "Paul J. Northrop <p.northrop@ucl.ac.uk>",
    "url": "https://github.com/paulnorthrop/smovie",
    "available": true
  },
  {
    "package": "threshr",
    "maintainer": "Paul J. Northrop <p.northrop@ucl.ac.uk>",
    "url": "https://github.com/paulnorthrop/threshr",
    "available": true
  }
]
