[
  {
    "package": "apyramid",
    "maintainer": "Zhian N. Kamvar <zkamvar@gmail.com>",
    "url": "https://github.com/r4epi/apyramid"
  },
  {
    "package": "epidict",
    "maintainer": "Alexander Spina <aspina@appliedepi.org>",
    "url": "https://github.com/r4epi/epidict"
  },
  {
    "package": "epikit",
    "maintainer": "Alexander Spina <aspina@appliedepi.org>",
    "url": "https://github.com/r4epi/epikit"
  },
  {
    "package": "epitabulate",
    "maintainer": "Alexander Spina <aspina@appliedepi.org>",
    "url": "https://github.com/r4epi/epitabulate"
  },
  {
    "package": "sitrep",
    "maintainer": "Alexander Spina <aspina@appliedepi.org>",
    "url": "https://github.com/r4epi/sitrep"
  }
]
