[
  {
    "package": "batsch",
    "maintainer": "Ramiro Magno <ramiro.magno@gmail.com>",
    "url": "https://github.com/ramiromagno/batsch"
  },
  {
    "package": "gwasrapidd",
    "maintainer": "Ramiro Magno <ramiro.magno@gmail.com>",
    "url": "https://github.com/ramiromagno/gwasrapidd"
  },
  {
    "package": "hgnc",
    "maintainer": "Ramiro Magno <rmagno@pattern.institute>",
    "url": "https://github.com/ramiromagno/hgnc"
  },
  {
    "package": "quincunx",
    "maintainer": "Ramiro Magno <rmagno@pattern.institute>",
    "url": "https://github.com/ramiromagno/quincunx"
  },
  {
    "package": "ruijter",
    "maintainer": "Ramiro Magno <ramiro.magno@gmail.com>",
    "url": "https://github.com/ramiromagno/ruijter"
  },
  {
    "package": "rutledge",
    "maintainer": "Ramiro Magno <ramiro.magno@gmail.com>",
    "url": "https://github.com/ramiromagno/rutledge"
  },
  {
    "package": "vermeulen",
    "maintainer": "Ramiro Magno <ramiro.magno@gmail.com>",
    "url": "https://github.com/ramiromagno/vermeulen"
  },
  {
    "package": "wig",
    "maintainer": "Ramiro Magno <ramiro.magno@gmail.com>",
    "url": "https://github.com/ramiromagno/wig"
  }
]
