[
  {
    "package": "galigor",
    "maintainer": "Alexey Seleznev <selesnow@gmail.com>",
    "url": "https://github.com/cran/galigor"
  },
  {
    "package": "getProxy",
    "maintainer": "Alexey Seleznev <selesnow@gmail.com>",
    "url": "https://github.com/selesnow/getproxy"
  },
  {
    "package": "racademyocean",
    "maintainer": "Alexey Seleznev <selesnow@gmail.com>",
    "url": "https://github.com/selesnow/racademyocean"
  },
  {
    "package": "ractivecampaign",
    "maintainer": "Alexey Seleznev <selesnow@gmail.com>",
    "url": "https://github.com/selesnow/ractivecampaign"
  },
  {
    "package": "rappsflyer",
    "maintainer": "Alexey Seleznev <selesnow@gmail.com>",
    "url": "https://github.com/selesnow/rappsflyer"
  },
  {
    "package": "rfacebookstat",
    "maintainer": "Alexey Seleznev <selesnow@gmail.com>",
    "url": "https://github.com/selesnow/rfacebookstat"
  },
  {
    "package": "rgoogleads",
    "maintainer": "Alexey Seleznev <selesnow@gmail.com>",
    "url": "https://github.com/selesnow/rgoogleads"
  },
  {
    "package": "ringostat",
    "maintainer": "Alexey Seleznev <selesnow@gmail.com>",
    "url": "https://github.com/selesnow/ringostat"
  },
  {
    "package": "rlinkedinads",
    "maintainer": "Alexey Seleznev <selesnow@gmail.com>",
    "url": "https://github.com/selesnow/rlinkedinads"
  },
  {
    "package": "rmytarget",
    "maintainer": "Alexey Seleznev <selesnow@gmail.com>",
    "url": "https://github.com/selesnow/rmytarget"
  },
  {
    "package": "rtgstat",
    "maintainer": "Alexey Seleznev <selesnow@gmail.com>",
    "url": "https://github.com/selesnow/rtgstat"
  },
  {
    "package": "rvkstat",
    "maintainer": "Alexey Seleznev <selesnow@gmail.com>",
    "url": "https://github.com/selesnow/rvkstat"
  },
  {
    "package": "ryandexdirect",
    "maintainer": "Alexey Seleznev <selesnow@gmail.com>",
    "url": "https://github.com/selesnow/ryandexdirect"
  },
  {
    "package": "rym",
    "maintainer": "Alexey Seleznev <selesnow@gmail.com>",
    "url": "https://github.com/selesnow/rym"
  },
  {
    "package": "rytstat",
    "maintainer": "Alexey Seleznev <selesnow@gmail.com>",
    "url": "https://github.com/selesnow/rytstat"
  },
  {
    "package": "timeperiodsR",
    "maintainer": "Alexey Seleznev <selesnow@gmail.com>",
    "url": "https://github.com/selesnow/timeperiodsr"
  }
]
