[
  {
    "package": "PamBinaries",
    "maintainer": "Taiki Sakai <taiki.sakai@noaa.gov>",
    "url": "https://github.com/taikisan21/pambinaries",
    "available": true
  },
  {
    "package": "PAMmisc",
    "maintainer": "Taiki Sakai <taiki.sakai@noaa.gov>",
    "url": "https://github.com/taikisan21/pammisc",
    "available": true
  },
  {
    "package": "PAMpal",
    "maintainer": "Taiki Sakai <taiki.sakai@noaa.gov>",
    "url": "https://github.com/taikisan21/pampal",
    "available": true
  }
]
