[
  {
    "package": "dendextend",
    "maintainer": "Tal Galili <tal.galili@gmail.com>",
    "url": "https://github.com/talgalili/dendextend",
    "available": true
  },
  {
    "package": "edfun",
    "maintainer": "Tal Galili <tal.galili@gmail.com>",
    "url": "https://github.com/talgalili/edfun",
    "available": true
  },
  {
    "package": "gplots",
    "maintainer": "Tal Galili <tal.galili@gmail.com>",
    "url": "https://github.com/talgalili/gplots",
    "available": true
  },
  {
    "package": "heatmaply",
    "maintainer": "Tal Galili <tal.galili@gmail.com>",
    "url": "https://github.com/talgalili/heatmaply",
    "available": true
  },
  {
    "package": "installr",
    "maintainer": "Tal Galili <tal.galili@gmail.com>",
    "url": "https://github.com/talgalili/installr",
    "available": true
  }
]
