[
  {
    "package": "dendextend",
    "maintainer": "Tal Galili <tal.galili@gmail.com>",
    "url": "https://github.com/talgalili/dendextend"
  },
  {
    "package": "edfun",
    "maintainer": "Tal Galili <tal.galili@gmail.com>",
    "url": "https://github.com/talgalili/edfun"
  },
  {
    "package": "gplots",
    "maintainer": "Tal Galili <tal.galili@gmail.com>",
    "url": "https://github.com/talgalili/gplots"
  },
  {
    "package": "heatmaply",
    "maintainer": "Tal Galili <tal.galili@gmail.com>",
    "url": "https://github.com/talgalili/heatmaply"
  },
  {
    "package": "installr",
    "maintainer": "Tal Galili <tal.galili@gmail.com>",
    "url": "https://github.com/talgalili/installr"
  }
]
