[
  {
    "package": "decorators",
    "maintainer": "Harel Lustiger <tidylab@gmail.com>",
    "url": "https://github.com/tidylab/decorators",
    "available": false
  },
  {
    "package": "microservices",
    "maintainer": "Harel Lustiger <tidylab@gmail.com>",
    "url": "https://github.com/tidylab/microservices",
    "available": true
  },
  {
    "package": "R6P",
    "maintainer": "Harel Lustiger <tidylab@gmail.com>",
    "url": "https://github.com/tidylab/r6p",
    "available": true
  },
  {
    "package": "tidylab",
    "maintainer": "Harel Lustiger <tidylab@gmail.com>",
    "url": "https://github.com/tidylab/tidylab",
    "available": true
  },
  {
    "package": "usethat",
    "maintainer": "Harel Lustiger <tidylab@gmail.com>",
    "url": "https://github.com/tidylab/usethat",
    "available": true
  }
]
