[
  {
    "package": "remify",
    "maintainer": "Giuseppe Arena <g.arena@uva.nl>",
    "url": "https://github.com/tilburgnetworkgroup/remify"
  },
  {
    "package": "remstats",
    "maintainer": "Giuseppe Arena <g.arena@uva.nl>",
    "url": "https://github.com/tilburgnetworkgroup/remstats"
  },
  {
    "package": "remstimate",
    "maintainer": "Giuseppe Arena <g.arena@uva.nl>",
    "url": "https://github.com/tilburgnetworkgroup/remstimate"
  },
  {
    "package": "remulate",
    "maintainer": "Rumana Lakdawala <rumanalakdawala@gmail.com>",
    "url": "https://github.com/tilburgnetworkgroup/remulate"
  }
]
