[
  {
    "package": "conflr",
    "maintainer": "Hiroaki Yutani <hiroaki.yutani@linecorp.com>",
    "url": "https://github.com/cran/conflr"
  },
  {
    "package": "datadogr",
    "maintainer": "Hiroaki Yutani <yutani.ini@gmail.com>",
    "url": "https://github.com/yutannihilation/k9"
  },
  {
    "package": "estatapi",
    "maintainer": "Hiroaki Yutani <yutani.ini@gmail.com>",
    "url": "https://github.com/yutannihilation/estatapi"
  },
  {
    "package": "gghighlight",
    "maintainer": "Hiroaki Yutani <yutani.ini@gmail.com>",
    "url": "https://github.com/yutannihilation/gghighlight"
  },
  {
    "package": "kntnr",
    "maintainer": "Hiroaki Yutani <yutani.ini@gmail.com>",
    "url": "https://github.com/yutannihilation/kntnr"
  },
  {
    "package": "kokudosuuchi",
    "maintainer": "Hiroaki Yutani <yutani.ini@gmail.com>",
    "url": "https://github.com/yutannihilation/kokudosuuchi"
  },
  {
    "package": "qiitr",
    "maintainer": "Hiroaki Yutani <yutani.ini@gmail.com>",
    "url": "https://github.com/yutannihilation/qiitr"
  },
  {
    "package": "string2path",
    "maintainer": "Hiroaki Yutani <yutani.ini@gmail.com>",
    "url": "https://github.com/yutannihilation/string2path"
  }
]
